trendlist/__init__.py
trendlist/py.typed
trendlist/simple.py
trendlist/trendlist.py
trendlist-0.3.7.dist-info/METADATA
trendlist-0.3.7.dist-info/LICENSE
trendlist-0.3.7.dist-info/WHEEL
trendlist-0.3.7.dist-info/RECORD
