Metadata-Version: 2.1
Name: trendlist
Version: 0.3.7
Summary: Define, manipulate and study lists of Trends.
Author: Jeffrey S. Haemer
Author-email: jeffrey.haemer@gmail.com
Requires-Python: >=3.10,<4.0
Classifier: Programming Language :: Python :: 3
Classifier: Programming Language :: Python :: 3.10
Classifier: Programming Language :: Python :: 3.11
Requires-Dist: blessed (>=1.19.1,<2.0.0)
Requires-Dist: myst-parser (>=0.18.1,<0.19.0)
Requires-Dist: sphinx (>=4.3.0,<5.0.0)
Requires-Dist: sphinx-autobuild (>=2021.3.14,<2022.0.0)
Requires-Dist: sphinx-rtd-theme (>=1.0.0,<2.0.0)
